hottohpy/__init__.py
hottohpy/client.py
hottohpy/const.py
hottohpy/hottoh.py
hottohpy/request.py
hottohpy-0.0.28.dist-info/LICENCE
hottohpy-0.0.28.dist-info/METADATA
hottohpy-0.0.28.dist-info/WHEEL
hottohpy-0.0.28.dist-info/top_level.txt
hottohpy-0.0.28.dist-info/RECORD
