Metadata-Version: 2.1
Name: hottohpy
Version: 0.0.28
Summary: Python lib to control Hottoh based stove Devices
Home-page: https://github.com/benlbrm/hottohpy
Author: benlbrm
Author-email: web@lebruman.fr
License: UNKNOWN
Project-URL: Bug Tracker, https://github.com/benlbrm/hottohpy/issues
Platform: UNKNOWN
Classifier: Programming Language :: Python :: 3
Classifier: License :: OSI Approved :: MIT License
Classifier: Operating System :: OS Independent
Classifier: Intended Audience :: Developers
Classifier: Intended Audience :: System Administrators
Classifier: Topic :: Home Automation
Requires-Python: >=3.6
License-File: LICENCE
